flinit/__init__.py
flinit/flinit.py
flinit-0.2.4.dist-info/LICENSE
flinit-0.2.4.dist-info/METADATA
flinit-0.2.4.dist-info/WHEEL
flinit-0.2.4.dist-info/entry_points.txt
flinit-0.2.4.dist-info/top_level.txt
flinit-0.2.4.dist-info/RECORD
