Metadata-Version: 2.1
Name: flinit
Version: 0.2.4
Summary: Flask App Initializer.
Home-page: https://github.com/TanmoySG/flinit
Author: Tanmoy Sen Gupta
Author-email: tanmoysps@gmail.com
License: MIT
Keywords: flask,python,project
Platform: UNKNOWN
Classifier: Programming Language :: Python :: 3
Classifier: License :: OSI Approved :: MIT License
Classifier: Operating System :: OS Independent
Requires-Dist: pip
Requires-Dist: emoji
